{
  "best_metric": -0.22534912824630737,
  "best_model_checkpoint": "TransPolymer_checkpoint/finetune_runs/checkpoint-49",
  "epoch": 49.0,
  "eval_steps": 500,
  "global_step": 49,
  "is_hyper_param_search": false,
  "is_local_process_zero": true,
  "is_world_process_zero": true,
  "log_history": [
    {
      "epoch": 1.0,
      "eval_loss": 241.23321533203125,
      "eval_mae": 7.407411575317383,
      "eval_mse": 241.23326110839844,
      "eval_r2": -0.6710065007209778,
      "eval_rmse": 15.531685713675719,
      "eval_runtime": 0.03,
      "eval_samples_per_second": 866.778,
      "eval_steps_per_second": 66.675,
      "step": 1
    },
    {
      "epoch": 2.0,
      "eval_loss": 241.23321533203125,
      "eval_mae": 7.407411575317383,
      "eval_mse": 241.23326110839844,
      "eval_r2": -0.6710065007209778,
      "eval_rmse": 15.531685713675719,
      "eval_runtime": 0.0296,
      "eval_samples_per_second": 879.543,
      "eval_steps_per_second": 67.657,
      "step": 2
    },
    {
      "epoch": 3.0,
      "eval_loss": 241.23321533203125,
      "eval_mae": 7.407411575317383,
      "eval_mse": 241.23326110839844,
      "eval_r2": -0.6710065007209778,
      "eval_rmse": 15.531685713675719,
      "eval_runtime": 0.0298,
      "eval_samples_per_second": 872.415,
      "eval_steps_per_second": 67.109,
      "step": 3
    },
    {
      "epoch": 4.0,
      "eval_loss": 241.23321533203125,
      "eval_mae": 7.407411575317383,
      "eval_mse": 241.23326110839844,
      "eval_r2": -0.6710065007209778,
      "eval_rmse": 15.531685713675719,
      "eval_runtime": 0.0295,
      "eval_samples_per_second": 881.078,
      "eval_steps_per_second": 67.775,
      "step": 4
    },
    {
      "epoch": 5.0,
      "eval_loss": 241.23321533203125,
      "eval_mae": 7.407411575317383,
      "eval_mse": 241.23326110839844,
      "eval_r2": -0.6710065007209778,
      "eval_rmse": 15.531685713675719,
      "eval_runtime": 0.0298,
      "eval_samples_per_second": 872.848,
      "eval_steps_per_second": 67.142,
      "step": 5
    },
    {
      "epoch": 6.0,
      "eval_loss": 241.23321533203125,
      "eval_mae": 7.407411575317383,
      "eval_mse": 241.23326110839844,
      "eval_r2": -0.6710065007209778,
      "eval_rmse": 15.531685713675719,
      "eval_runtime": 0.0294,
      "eval_samples_per_second": 883.19,
      "eval_steps_per_second": 67.938,
      "step": 6
    },
    {
      "epoch": 7.0,
      "eval_loss": 241.23321533203125,
      "eval_mae": 7.407411575317383,
      "eval_mse": 241.23326110839844,
      "eval_r2": -0.6710065007209778,
      "eval_rmse": 15.531685713675719,
      "eval_runtime": 0.0295,
      "eval_samples_per_second": 880.736,
      "eval_steps_per_second": 67.749,
      "step": 7
    },
    {
      "epoch": 8.0,
      "eval_loss": 236.78125,
      "eval_mae": 7.238037109375,
      "eval_mse": 236.78126525878906,
      "eval_r2": -0.6421611905097961,
      "eval_rmse": 15.387698504285462,
      "eval_runtime": 0.0302,
      "eval_samples_per_second": 860.716,
      "eval_steps_per_second": 66.209,
      "step": 8
    },
    {
      "epoch": 9.0,
      "eval_loss": 232.70677185058594,
      "eval_mae": 7.07815408706665,
      "eval_mse": 232.70675659179688,
      "eval_r2": -0.6141716241836548,
      "eval_rmse": 15.254728991096396,
      "eval_runtime": 0.03,
      "eval_samples_per_second": 867.516,
      "eval_steps_per_second": 66.732,
      "step": 9
    },
    {
      "epoch": 10.0,
      "grad_norm": 1124.8828125,
      "learning_rate": 2.8199999999999998e-05,
      "loss": 4471.3211,
      "step": 10
    },
    {
      "epoch": 10.0,
      "eval_loss": 228.96282958984375,
      "eval_mae": 6.928043365478516,
      "eval_mse": 228.96286010742188,
      "eval_r2": -0.5884799361228943,
      "eval_rmse": 15.13151876407064,
      "eval_runtime": 0.0287,
      "eval_samples_per_second": 905.085,
      "eval_steps_per_second": 69.622,
      "step": 10
    },
    {
      "epoch": 11.0,
      "eval_loss": 225.48045349121094,
      "eval_mae": 6.786943435668945,
      "eval_mse": 225.48046875,
      "eval_r2": -0.5666115880012512,
      "eval_rmse": 15.016007084108612,
      "eval_runtime": 0.0298,
      "eval_samples_per_second": 871.154,
      "eval_steps_per_second": 67.012,
      "step": 11
    },
    {
      "epoch": 12.0,
      "eval_loss": 222.24984741210938,
      "eval_mae": 6.653050899505615,
      "eval_mse": 222.2498779296875,
      "eval_r2": -0.5453788638114929,
      "eval_rmse": 14.908047421768133,
      "eval_runtime": 0.0302,
      "eval_samples_per_second": 861.73,
      "eval_steps_per_second": 66.287,
      "step": 12
    },
    {
      "epoch": 13.0,
      "eval_loss": 219.22378540039062,
      "eval_mae": 6.525886535644531,
      "eval_mse": 219.2237548828125,
      "eval_r2": -0.5261346101760864,
      "eval_rmse": 14.806206633800992,
      "eval_runtime": 0.0302,
      "eval_samples_per_second": 860.587,
      "eval_steps_per_second": 66.199,
      "step": 13
    },
    {
      "epoch": 14.0,
      "eval_loss": 216.3760528564453,
      "eval_mae": 6.404229640960693,
      "eval_mse": 216.3760528564453,
      "eval_r2": -0.5079428553581238,
      "eval_rmse": 14.709726471163401,
      "eval_runtime": 0.03,
      "eval_samples_per_second": 865.402,
      "eval_steps_per_second": 66.569,
      "step": 14
    },
    {
      "epoch": 15.0,
      "eval_loss": 213.69387817382812,
      "eval_mae": 6.288076400756836,
      "eval_mse": 213.69387817382812,
      "eval_r2": -0.4910908341407776,
      "eval_rmse": 14.618272065255459,
      "eval_runtime": 0.0297,
      "eval_samples_per_second": 874.535,
      "eval_steps_per_second": 67.272,
      "step": 15
    },
    {
      "epoch": 16.0,
      "eval_loss": 211.17784118652344,
      "eval_mae": 6.176832675933838,
      "eval_mse": 211.1778106689453,
      "eval_r2": -0.4749021530151367,
      "eval_rmse": 14.531958253069176,
      "eval_runtime": 0.0301,
      "eval_samples_per_second": 863.176,
      "eval_steps_per_second": 66.398,
      "step": 16
    },
    {
      "epoch": 17.0,
      "eval_loss": 208.8142852783203,
      "eval_mae": 6.070685863494873,
      "eval_mse": 208.81430053710938,
      "eval_r2": -0.45878738164901733,
      "eval_rmse": 14.450408317314407,
      "eval_runtime": 0.0303,
      "eval_samples_per_second": 858.399,
      "eval_steps_per_second": 66.031,
      "step": 17
    },
    {
      "epoch": 18.0,
      "eval_loss": 206.57562255859375,
      "eval_mae": 5.970262050628662,
      "eval_mse": 206.5756378173828,
      "eval_r2": -0.44266945123672485,
      "eval_rmse": 14.372739398506564,
      "eval_runtime": 0.0302,
      "eval_samples_per_second": 859.787,
      "eval_steps_per_second": 66.137,
      "step": 18
    },
    {
      "epoch": 19.0,
      "eval_loss": 204.41416931152344,
      "eval_mae": 5.876877307891846,
      "eval_mse": 204.4141845703125,
      "eval_r2": -0.4274810552597046,
      "eval_rmse": 14.29734886509777,
      "eval_runtime": 0.0299,
      "eval_samples_per_second": 868.275,
      "eval_steps_per_second": 66.79,
      "step": 19
    },
    {
      "epoch": 20.0,
      "grad_norm": 1062.5672607421875,
      "learning_rate": 2.22e-05,
      "loss": 4307.1445,
      "step": 20
    },
    {
      "epoch": 20.0,
      "eval_loss": 202.4022674560547,
      "eval_mae": 5.7882890701293945,
      "eval_mse": 202.40225219726562,
      "eval_r2": -0.4128420948982239,
      "eval_rmse": 14.226814548494882,
      "eval_runtime": 0.0287,
      "eval_samples_per_second": 907.216,
      "eval_steps_per_second": 69.786,
      "step": 20
    },
    {
      "epoch": 21.0,
      "eval_loss": 200.46359252929688,
      "eval_mae": 5.707389831542969,
      "eval_mse": 200.46360778808594,
      "eval_r2": -0.3992502689361572,
      "eval_rmse": 14.158517146512411,
      "eval_runtime": 0.0301,
      "eval_samples_per_second": 864.291,
      "eval_steps_per_second": 66.484,
      "step": 21
    },
    {
      "epoch": 22.0,
      "eval_loss": 198.62228393554688,
      "eval_mae": 5.632220268249512,
      "eval_mse": 198.62225341796875,
      "eval_r2": -0.38661521673202515,
      "eval_rmse": 14.093340747245444,
      "eval_runtime": 0.0301,
      "eval_samples_per_second": 863.483,
      "eval_steps_per_second": 66.422,
      "step": 22
    },
    {
      "epoch": 23.0,
      "eval_loss": 196.88800048828125,
      "eval_mae": 5.565262794494629,
      "eval_mse": 196.88800048828125,
      "eval_r2": -0.37488389015197754,
      "eval_rmse": 14.031678462973746,
      "eval_runtime": 0.0301,
      "eval_samples_per_second": 864.874,
      "eval_steps_per_second": 66.529,
      "step": 23
    },
    {
      "epoch": 24.0,
      "eval_loss": 195.26663208007812,
      "eval_mae": 5.503280162811279,
      "eval_mse": 195.26663208007812,
      "eval_r2": -0.3631453514099121,
      "eval_rmse": 13.973783742425605,
      "eval_runtime": 0.0301,
      "eval_samples_per_second": 864.332,
      "eval_steps_per_second": 66.487,
      "step": 24
    },
    {
      "epoch": 25.0,
      "eval_loss": 193.7324981689453,
      "eval_mae": 5.443743705749512,
      "eval_mse": 193.73252868652344,
      "eval_r2": -0.35153746604919434,
      "eval_rmse": 13.91878330481955,
      "eval_runtime": 0.0302,
      "eval_samples_per_second": 861.805,
      "eval_steps_per_second": 66.293,
      "step": 25
    },
    {
      "epoch": 26.0,
      "eval_loss": 192.28414916992188,
      "eval_mae": 5.387266159057617,
      "eval_mse": 192.2841033935547,
      "eval_r2": -0.34034597873687744,
      "eval_rmse": 13.866654369153169,
      "eval_runtime": 0.0301,
      "eval_samples_per_second": 862.52,
      "eval_steps_per_second": 66.348,
      "step": 26
    },
    {
      "epoch": 27.0,
      "eval_loss": 190.90357971191406,
      "eval_mae": 5.332700729370117,
      "eval_mse": 190.90359497070312,
      "eval_r2": -0.3300197720527649,
      "eval_rmse": 13.816786709314982,
      "eval_runtime": 0.0299,
      "eval_samples_per_second": 870.243,
      "eval_steps_per_second": 66.942,
      "step": 27
    },
    {
      "epoch": 28.0,
      "eval_loss": 189.57138061523438,
      "eval_mae": 5.279971122741699,
      "eval_mse": 189.57138061523438,
      "eval_r2": -0.32085615396499634,
      "eval_rmse": 13.768492314528645,
      "eval_runtime": 0.0301,
      "eval_samples_per_second": 863.873,
      "eval_steps_per_second": 66.452,
      "step": 28
    },
    {
      "epoch": 29.0,
      "eval_loss": 188.32522583007812,
      "eval_mae": 5.230299949645996,
      "eval_mse": 188.32522583007812,
      "eval_r2": -0.3119938373565674,
      "eval_rmse": 13.7231638418434,
      "eval_runtime": 0.0302,
      "eval_samples_per_second": 862.268,
      "eval_steps_per_second": 66.328,
      "step": 29
    },
    {
      "epoch": 30.0,
      "grad_norm": 1071.1519775390625,
      "learning_rate": 1.62e-05,
      "loss": 4168.4387,
      "step": 30
    },
    {
      "epoch": 30.0,
      "eval_loss": 187.15232849121094,
      "eval_mae": 5.182843208312988,
      "eval_mse": 187.15232849121094,
      "eval_r2": -0.3039759397506714,
      "eval_rmse": 13.680362878637794,
      "eval_runtime": 0.0288,
      "eval_samples_per_second": 903.585,
      "eval_steps_per_second": 69.507,
      "step": 30
    },
    {
      "epoch": 31.0,
      "eval_loss": 186.05906677246094,
      "eval_mae": 5.140517234802246,
      "eval_mse": 186.05906677246094,
      "eval_r2": -0.2964075207710266,
      "eval_rmse": 13.640347018036636,
      "eval_runtime": 0.0301,
      "eval_samples_per_second": 863.777,
      "eval_steps_per_second": 66.444,
      "step": 31
    },
    {
      "epoch": 32.0,
      "eval_loss": 185.03981018066406,
      "eval_mae": 5.1029205322265625,
      "eval_mse": 185.03982543945312,
      "eval_r2": -0.2890075445175171,
      "eval_rmse": 13.602934442224337,
      "eval_runtime": 0.0301,
      "eval_samples_per_second": 864.421,
      "eval_steps_per_second": 66.494,
      "step": 32
    },
    {
      "epoch": 33.0,
      "eval_loss": 184.07650756835938,
      "eval_mae": 5.0667033195495605,
      "eval_mse": 184.07650756835938,
      "eval_r2": -0.2823922634124756,
      "eval_rmse": 13.567479779544888,
      "eval_runtime": 0.0303,
      "eval_samples_per_second": 857.677,
      "eval_steps_per_second": 65.975,
      "step": 33
    },
    {
      "epoch": 34.0,
      "eval_loss": 183.19081115722656,
      "eval_mae": 5.032919406890869,
      "eval_mse": 183.19078063964844,
      "eval_r2": -0.27614718675613403,
      "eval_rmse": 13.534798876955964,
      "eval_runtime": 0.0301,
      "eval_samples_per_second": 864.359,
      "eval_steps_per_second": 66.489,
      "step": 34
    },
    {
      "epoch": 35.0,
      "eval_loss": 182.36219787597656,
      "eval_mae": 5.001067161560059,
      "eval_mse": 182.36215209960938,
      "eval_r2": -0.2705867886543274,
      "eval_rmse": 13.50415314263021,
      "eval_runtime": 0.0305,
      "eval_samples_per_second": 853.475,
      "eval_steps_per_second": 65.652,
      "step": 35
    },
    {
      "epoch": 36.0,
      "eval_loss": 181.57379150390625,
      "eval_mae": 4.970409393310547,
      "eval_mse": 181.57379150390625,
      "eval_r2": -0.2656638026237488,
      "eval_rmse": 13.474931966578023,
      "eval_runtime": 0.0303,
      "eval_samples_per_second": 859.428,
      "eval_steps_per_second": 66.11,
      "step": 36
    },
    {
      "epoch": 37.0,
      "eval_loss": 180.83229064941406,
      "eval_mae": 4.944602012634277,
      "eval_mse": 180.8323516845703,
      "eval_r2": -0.26096445322036743,
      "eval_rmse": 13.447392003082618,
      "eval_runtime": 0.0303,
      "eval_samples_per_second": 857.92,
      "eval_steps_per_second": 65.994,
      "step": 37
    },
    {
      "epoch": 38.0,
      "eval_loss": 180.09890747070312,
      "eval_mae": 4.922205924987793,
      "eval_mse": 180.0989532470703,
      "eval_r2": -0.2567713260650635,
      "eval_rmse": 13.42009512809318,
      "eval_runtime": 0.0303,
      "eval_samples_per_second": 857.596,
      "eval_steps_per_second": 65.969,
      "step": 38
    },
    {
      "epoch": 39.0,
      "eval_loss": 179.38134765625,
      "eval_mae": 4.903884410858154,
      "eval_mse": 179.38133239746094,
      "eval_r2": -0.2530527710914612,
      "eval_rmse": 13.393331639194967,
      "eval_runtime": 0.0303,
      "eval_samples_per_second": 858.413,
      "eval_steps_per_second": 66.032,
      "step": 39
    },
    {
      "epoch": 40.0,
      "grad_norm": 1105.3349609375,
      "learning_rate": 1.02e-05,
      "loss": 4094.2957,
      "step": 40
    },
    {
      "epoch": 40.0,
      "eval_loss": 178.72361755371094,
      "eval_mae": 4.88858699798584,
      "eval_mse": 178.72361755371094,
      "eval_r2": -0.24944788217544556,
      "eval_rmse": 13.36875527316253,
      "eval_runtime": 0.0289,
      "eval_samples_per_second": 898.878,
      "eval_steps_per_second": 69.144,
      "step": 40
    },
    {
      "epoch": 41.0,
      "eval_loss": 178.1188201904297,
      "eval_mae": 4.874483585357666,
      "eval_mse": 178.1188201904297,
      "eval_r2": -0.24617081880569458,
      "eval_rmse": 13.346116296152589,
      "eval_runtime": 0.0302,
      "eval_samples_per_second": 861.771,
      "eval_steps_per_second": 66.29,
      "step": 41
    },
    {
      "epoch": 42.0,
      "eval_loss": 177.5748748779297,
      "eval_mae": 4.8618316650390625,
      "eval_mse": 177.57489013671875,
      "eval_r2": -0.24301612377166748,
      "eval_rmse": 13.32572287482817,
      "eval_runtime": 0.0305,
      "eval_samples_per_second": 851.343,
      "eval_steps_per_second": 65.488,
      "step": 42
    },
    {
      "epoch": 43.0,
      "eval_loss": 177.08941650390625,
      "eval_mae": 4.850033283233643,
      "eval_mse": 177.08946228027344,
      "eval_r2": -0.24018913507461548,
      "eval_rmse": 13.307496469294044,
      "eval_runtime": 0.0306,
      "eval_samples_per_second": 850.5,
      "eval_steps_per_second": 65.423,
      "step": 43
    },
    {
      "epoch": 44.0,
      "eval_loss": 176.63653564453125,
      "eval_mae": 4.839178562164307,
      "eval_mse": 176.63653564453125,
      "eval_r2": -0.23729801177978516,
      "eval_rmse": 13.290467848970978,
      "eval_runtime": 0.0305,
      "eval_samples_per_second": 852.727,
      "eval_steps_per_second": 65.594,
      "step": 44
    },
    {
      "epoch": 45.0,
      "eval_loss": 176.23306274414062,
      "eval_mae": 4.829339027404785,
      "eval_mse": 176.23306274414062,
      "eval_r2": -0.2344207763671875,
      "eval_rmse": 13.275280138066414,
      "eval_runtime": 0.0303,
      "eval_samples_per_second": 857.064,
      "eval_steps_per_second": 65.928,
      "step": 45
    },
    {
      "epoch": 46.0,
      "eval_loss": 175.86676025390625,
      "eval_mae": 4.820547103881836,
      "eval_mse": 175.86679077148438,
      "eval_r2": -0.2318224310874939,
      "eval_rmse": 13.261477699392492,
      "eval_runtime": 0.0302,
      "eval_samples_per_second": 860.601,
      "eval_steps_per_second": 66.2,
      "step": 46
    },
    {
      "epoch": 47.0,
      "eval_loss": 175.53384399414062,
      "eval_mae": 4.812470436096191,
      "eval_mse": 175.53382873535156,
      "eval_r2": -0.22949457168579102,
      "eval_rmse": 13.248918021308441,
      "eval_runtime": 0.0304,
      "eval_samples_per_second": 854.806,
      "eval_steps_per_second": 65.754,
      "step": 47
    },
    {
      "epoch": 48.0,
      "eval_loss": 175.23411560058594,
      "eval_mae": 4.805278301239014,
      "eval_mse": 175.234130859375,
      "eval_r2": -0.22730422019958496,
      "eval_rmse": 13.237602912135376,
      "eval_runtime": 0.0305,
      "eval_samples_per_second": 852.981,
      "eval_steps_per_second": 65.614,
      "step": 48
    },
    {
      "epoch": 49.0,
      "eval_loss": 174.952392578125,
      "eval_mae": 4.798688888549805,
      "eval_mse": 174.95240783691406,
      "eval_r2": -0.22534912824630737,
      "eval_rmse": 13.226957618323047,
      "eval_runtime": 0.0306,
      "eval_samples_per_second": 850.573,
      "eval_steps_per_second": 65.429,
      "step": 49
    }
  ],
  "logging_steps": 10,
  "max_steps": 50,
  "num_input_tokens_seen": 0,
  "num_train_epochs": 50,
  "save_steps": 500,
  "stateful_callbacks": {
    "EarlyStoppingCallback": {
      "args": {
        "early_stopping_patience": 10,
        "early_stopping_threshold": 0.0
      },
      "attributes": {
        "early_stopping_patience_counter": 0
      }
    },
    "TrainerControl": {
      "args": {
        "should_epoch_stop": false,
        "should_evaluate": false,
        "should_log": false,
        "should_save": true,
        "should_training_stop": false
      },
      "attributes": {}
    }
  },
  "total_flos": 29209061403648.0,
  "train_batch_size": 16,
  "trial_name": null,
  "trial_params": null
}
